translategemma_cli/__init__.py
translategemma_cli/backends.py
translategemma_cli/chunker.py
translategemma_cli/cli.py
translategemma_cli/config.py
translategemma_cli/detector.py
translategemma_cli/model.py
translategemma_cli/translator.py
translategemma_cli-0.2.0.dist-info/licenses/LICENSE
translategemma_cli-0.2.0.dist-info/METADATA
translategemma_cli-0.2.0.dist-info/WHEEL
translategemma_cli-0.2.0.dist-info/entry_points.txt
translategemma_cli-0.2.0.dist-info/top_level.txt
translategemma_cli-0.2.0.dist-info/RECORD
