Metadata-Version: 2.4
Name: translategemma-cli
Version: 0.2.0
Summary: Local CLI for TranslateGemma translation (multi-platform, multi-model)
Author: Jacky Chan
License: MIT
Project-URL: Homepage, https://github.com/jhkchan/translategemma-cli
Keywords: translation,cantonese,mlx,apple-silicon,gemma,pytorch,cuda
Classifier: Development Status :: 3 - Alpha
Classifier: Environment :: Console
Classifier: Intended Audience :: Developers
Classifier: License :: OSI Approved :: MIT License
Classifier: Operating System :: MacOS
Classifier: Operating System :: POSIX :: Linux
Classifier: Operating System :: Microsoft :: Windows
Classifier: Programming Language :: Python :: 3.11
Classifier: Programming Language :: Python :: 3.12
Classifier: Topic :: Text Processing :: Linguistic
Requires-Python: >=3.11
License-File: LICENSE
Requires-Dist: transformers<5.0,>=4.42.0
Requires-Dist: huggingface-hub<1.0,>=0.24.0
Requires-Dist: typer<1.0,>=0.12.0
Requires-Dist: pyyaml<7.0,>=6.0
Requires-Dist: rich<15.0,>=13.0.0
Requires-Dist: prompt-toolkit<4.0,>=3.0.0
Requires-Dist: regex>=2024.0.0
Requires-Dist: accelerate<1.0,>=0.25.0
Provides-Extra: mlx
Requires-Dist: mlx>=0.22.0; extra == "mlx"
Requires-Dist: mlx-lm>=0.20.0; extra == "mlx"
Provides-Extra: cuda
Requires-Dist: torch<3.0,>=2.0.0; extra == "cuda"
Requires-Dist: bitsandbytes<1.0,>=0.41.0; extra == "cuda"
Provides-Extra: cpu
Requires-Dist: torch<3.0,>=2.0.0; extra == "cpu"
Provides-Extra: dev
Requires-Dist: pytest<9.0,>=7.0.0; extra == "dev"
Requires-Dist: pytest-cov<8.0,>=4.0.0; extra == "dev"
Requires-Dist: black>=23.0.0; extra == "dev"
Requires-Dist: ruff>=0.1.0; extra == "dev"
Dynamic: license-file
